statistics_core/__init__.py
statistics_core/module.py
statistics_core-0.0.7.dist-info/LICENSE
statistics_core-0.0.7.dist-info/METADATA
statistics_core-0.0.7.dist-info/WHEEL
statistics_core-0.0.7.dist-info/top_level.txt
statistics_core-0.0.7.dist-info/RECORD
